arango_datasets/__init__.py
arango_datasets/datasets.py
arango_datasets/utils.py
arango_datasets-1.2.3.dist-info/AUTHORS.rst
arango_datasets-1.2.3.dist-info/METADATA
arango_datasets-1.2.3.dist-info/WHEEL
arango_datasets-1.2.3.dist-info/top_level.txt
arango_datasets-1.2.3.dist-info/RECORD
