Metadata-Version: 2.2
Name: arango_datasets
Version: 1.2.3
Summary: Package for fetching and loading datasets for ArangoDB deployments.
Author-email: Christopher Woodward <christopher@arangodb.com>
Project-URL: Homepage, https://github.com/arangoml/arangodb_datasets
Classifier: Development Status :: 2 - Pre-Alpha
Classifier: Intended Audience :: Developers
Classifier: License :: OSI Approved :: Apache Software License
Classifier: Natural Language :: English
Classifier: Programming Language :: Python :: 3
Classifier: Operating System :: OS Independent
Requires-Python: >=3.8
License-File: AUTHORS.rst
Requires-Dist: python-arango>=7.4.1
Requires-Dist: requests>=2.28.1
Requires-Dist: rich>=12.6.0
Provides-Extra: dev
Requires-Dist: bandit>=1.7.4; extra == "dev"
Requires-Dist: black>=22.10.0; extra == "dev"
Requires-Dist: flake8>=5.0.4; extra == "dev"
Requires-Dist: Flake8-pyproject; extra == "dev"
Requires-Dist: isort>=5.10.1; extra == "dev"
Requires-Dist: mypy>=0.982; extra == "dev"
Requires-Dist: pre-commit>=2.20.0; extra == "dev"
Requires-Dist: pytest>=7.1.3; extra == "dev"
Requires-Dist: pytest-cov>=4.0.0; extra == "dev"
Requires-Dist: sphinx>=5.3.0; extra == "dev"
Requires-Dist: types-requests>=2.28.11.2; extra == "dev"
Requires-Dist: types-setuptools>=65.5.0.1; extra == "dev"
